callback/__init__.py
callback/adversarial.py
callback/early_stopping.py
callback/ema.py
callback/file_writer.py
callback/logger.py
callback/model_checkpoint.py
callback/progressbar.py
data/Vocabulary.py
data/__init__.py
data/embedding.py
data/tokenizer.py
losses/__init__.py
losses/focal_loss.py
losses/hard_mining.py
losses/kd_loss.py
losses/kl_divergence.py
losses/label_smoothing.py
losses/span_loss.py
losses/symmetric_ce.py
losses/triplet_loss.py
metrics/__init__.py
metrics/base.py
metrics/classification.py
metrics/regression.py
metrics/sequence_labeling.py
metrics/utils.py
models/__init__.py
models/bases/__init__.py
models/bases/configuration_base.py
models/bases/model_base.py
models/nn/__init__.py
models/nn/bert_for_attr.py
models/nn/bert_for_multilabel.py
models/nn/bert_for_ner.py
models/nn/bert_for_relation.py
models/nn/bert_for_siamese.py
models/nn/bert_for_triple.py
models/nn/bert_with_mdp.py
models/nn/lstm_crf.py
models/transformer/__init__.py
models/transformer/configuration_albert.py
models/transformer/convert_albert_original_tf_checkpoint_to_pytorch.py
models/transformer/modeling_albert.py
models/transformer/modeling_bert_for_theseus.py
models/transformer/utils.py
optims/__init__.py
optims/adabelief.py
optims/adabound.py
optims/adafactor.py
optims/adamod.py
optims/adamp.py
optims/adamw.py
optims/adax.py
optims/lamb.py
optims/lars.py
optims/lookahead.py
optims/lr_scheduler.py
optims/nadam.py
optims/novograd.py
optims/planradam.py
optims/priorwd.py
optims/radam.py
optims/ralamb.py
optims/ralars.py
optims/ranger_adabelief.py
optims/sgdp.py
optims/sgdw.py
optims/shampoo.py
optims/utils.py
processor/__init__.py
processor/base.py
processor/classifier_processor.py
processor/sequence_labeling_processor.py
processor/utils.py
trainer/__init__.py
trainer/base.py
trainer/classifier_trainer.py
trainer/sequence_labeling_trainer.py
trainer/triple_trainer.py
utils/__init__.py
utils/build_argparse.py
utils/download_clue_data.py
utils/download_glue_data.py
utils/paths.py
torchblocks-1.0.0.dist-info/LICENSE
torchblocks-1.0.0.dist-info/METADATA
torchblocks-1.0.0.dist-info/WHEEL
torchblocks-1.0.0.dist-info/top_level.txt
torchblocks-1.0.0.dist-info/RECORD
