Metadata-Version: 2.1
Name: torchblocks
Version: 1.0.0
Summary: A PyTorch-based toolkit for natural language processing
Home-page: https://github.com/lonePatient/TorchBlocks
Author: lonePatient
Author-email: liuweitangmath@163.com
License: MIT
Keywords: NLP deep learning transformer pytorch BERT
Platform: UNKNOWN
Classifier: Development Status :: 5 - Production/Stable
Classifier: Intended Audience :: Developers
Classifier: Intended Audience :: Education
Classifier: Intended Audience :: Science/Research
Classifier: License :: OSI Approved :: MIT License
Classifier: Operating System :: OS Independent
Classifier: Programming Language :: Python :: 3
Classifier: Programming Language :: Python :: 3.6
Classifier: Programming Language :: Python :: 3.7
Classifier: Topic :: Scientific/Engineering :: Artificial Intelligence
Requires-Python: >=3.6.0
Requires-Dist: scikit-learn
Requires-Dist: tokenizers (>=0.7.0)
Requires-Dist: torch (>=1.6.0)
Requires-Dist: transformers (>=4.1.1)
Requires-Dist: sentencepiece
Requires-Dist: sacremoses
